<?xml version="1.0" encoding="utf-8"?>
<savedqueries xmlns:xsi="http://www.w3.org/2001/XMLSchema-instance">
  <savedquery>
    <IsCustomizable>1</IsCustomizable>
    <CanBeDeleted>1</CanBeDeleted>
    <isquickfindquery>0</isquickfindquery>
    <isprivate>0</isprivate>
    <isdefault>0</isdefault>
    <savedqueryid>{28adc7b3-3a55-eb11-a812-000d3aff12c2}</savedqueryid>
    <layoutxml>
      <grid name="resultset" jump="qm_name" select="1" icon="1" preview="1">
        <row name="result" id="qm_tylegislationcharacteristicid">
          <cell name="qm_name" width="300" />
          <cell name="qm_legislationcharacteristicelbl" width="263" />
          <cell name="qm_legislationcharacteristicflbl" width="277" />
        </row>
      </grid>
    </layoutxml>
    <querytype>0</querytype>
    <fetchxml>
      <fetch version="1.0" output-format="xml-platform" mapping="logical" distinct="false">
        <entity name="qm_tylegislationcharacteristic">
          <attribute name="qm_name" />
          <attribute name="qm_legislationcharacteristicelbl" />
          <attribute name="qm_legislationcharacteristicflbl" />
          <order attribute="qm_name" descending="false" />
          <filter type="and">
            <condition attribute="statecode" operator="eq" value="0" />
            <condition attribute="qm_categoryid" operator="null" />
          </filter>
          <attribute name="qm_tylegislationcharacteristicid" />
        </entity>
      </fetch>
    </fetchxml>
    <IntroducedVersion>1.0.0.1</IntroducedVersion>
    <LocalizedNames>
      <LocalizedName description="Legislation Characteristics Hierarchy" languagecode="1033" />
      <LocalizedName description="Hiérarchie des caractéristiques de la législation" languagecode="1036" />
    </LocalizedNames>
    <Descriptions>
      <Description description="Only Categories - parent Characteristics " languagecode="1033" />
      <Description description="Catégories uniquement - caractéristiques des parents" languagecode="1036" />
    </Descriptions>
  </savedquery>
</savedqueries>