<?xml version="1.0" encoding="utf-8"?>
<savedqueries xmlns:xsi="http://www.w3.org/2001/XMLSchema-instance">
  <savedquery>
    <IsCustomizable>1</IsCustomizable>
    <CanBeDeleted>0</CanBeDeleted>
    <isquickfindquery>0</isquickfindquery>
    <isprivate>0</isprivate>
    <isdefault>1</isdefault>
    <savedqueryid>{75a5521e-3542-426a-b032-97581c3577f1}</savedqueryid>
    <layoutxml>
      <grid name="resultset" jump="ts_name" select="1" icon="1" preview="1">
        <row name="result" id="ts_enforcementactionid">
          <cell name="ts_name" width="118" />
          <cell name="ts_type" width="264" />
          <cell name="createdon" width="125" />
        </row>
      </grid>
    </layoutxml>
    <querytype>0</querytype>
    <fetchxml>
      <fetch version="1.0" mapping="logical">
        <entity name="ts_enforcementaction">
          <attribute name="ts_enforcementactionid" />
          <attribute name="ts_name" />
          <attribute name="createdon" />
          <order attribute="ts_name" descending="false" />
          <filter type="and">
            <condition attribute="statecode" operator="eq" value="0" />
          </filter>
          <attribute name="ts_type" />
        </entity>
      </fetch>
    </fetchxml>
    <IntroducedVersion>1.0</IntroducedVersion>
    <LocalizedNames>
      <LocalizedName description="Active Enforcement Actions" languagecode="1033" />
      <LocalizedName description="Active Enforcement Actions (FR)" languagecode="1036" />
    </LocalizedNames>
  </savedquery>
</savedqueries>