<?xml version="1.0" encoding="utf-8"?>
<EntityRelationships xmlns:xsi="http://www.w3.org/2001/XMLSchema-instance">
  <EntityRelationship Name="ovs_cysafetyassessment_ovs_cancellationrequests">
    <EntityRelationshipType>OneToMany</EntityRelationshipType>
    <IsCustomizable>1</IsCustomizable>
    <IntroducedVersion>4.2.1.4</IntroducedVersion>
    <IsHierarchical>0</IsHierarchical>
    <ReferencingEntityName>ovs_cancellationrequest</ReferencingEntityName>
    <ReferencedEntityName>ovs_CYSafetyAssessment</ReferencedEntityName>
    <CascadeAssign>Cascade</CascadeAssign>
    <CascadeDelete>Cascade</CascadeDelete>
    <CascadeReparent>Cascade</CascadeReparent>
    <CascadeShare>Cascade</CascadeShare>
    <CascadeUnshare>Cascade</CascadeUnshare>
    <ReferencingAttributeName>RegardingObjectId</ReferencingAttributeName>
    <RelationshipDescription>
      <Descriptions>
        <Description description="Unique identifier of the object with which the activity is associated." languagecode="1033" />
        <Description description="Identificateur unique de l'objet auquel l'activité est associée." languagecode="1036" />
      </Descriptions>
    </RelationshipDescription>
  </EntityRelationship>
  <EntityRelationship Name="ovs_cysafetyassessment_ovs_CYActions">
    <EntityRelationshipType>OneToMany</EntityRelationshipType>
    <IsCustomizable>1</IsCustomizable>
    <IntroducedVersion>4.2.1.4</IntroducedVersion>
    <IsHierarchical>0</IsHierarchical>
    <ReferencingEntityName>ovs_CYAction</ReferencingEntityName>
    <ReferencedEntityName>ovs_CYSafetyAssessment</ReferencedEntityName>
    <CascadeAssign>Cascade</CascadeAssign>
    <CascadeDelete>Cascade</CascadeDelete>
    <CascadeReparent>Cascade</CascadeReparent>
    <CascadeShare>Cascade</CascadeShare>
    <CascadeUnshare>Cascade</CascadeUnshare>
    <ReferencingAttributeName>RegardingObjectId</ReferencingAttributeName>
    <RelationshipDescription>
      <Descriptions>
        <Description description="Unique identifier of the object with which the activity is associated." languagecode="1033" />
        <Description description="Identificateur unique de l'objet auquel l'activité est associée." languagecode="1036" />
      </Descriptions>
    </RelationshipDescription>
  </EntityRelationship>
  <EntityRelationship Name="ovs_cysafetyassessment_ovs_revisedquarterrequests">
    <EntityRelationshipType>OneToMany</EntityRelationshipType>
    <IsCustomizable>1</IsCustomizable>
    <IntroducedVersion>4.2.1.4</IntroducedVersion>
    <IsHierarchical>0</IsHierarchical>
    <ReferencingEntityName>ovs_revisedquarterrequest</ReferencingEntityName>
    <ReferencedEntityName>ovs_CYSafetyAssessment</ReferencedEntityName>
    <CascadeAssign>Cascade</CascadeAssign>
    <CascadeDelete>Cascade</CascadeDelete>
    <CascadeReparent>Cascade</CascadeReparent>
    <CascadeShare>Cascade</CascadeShare>
    <CascadeUnshare>Cascade</CascadeUnshare>
    <ReferencingAttributeName>RegardingObjectId</ReferencingAttributeName>
    <RelationshipDescription>
      <Descriptions>
        <Description description="Unique identifier of the object with which the activity is associated." languagecode="1033" />
        <Description description="Identificateur unique de l'objet auquel l'activité est associée." languagecode="1036" />
      </Descriptions>
    </RelationshipDescription>
  </EntityRelationship>
  <EntityRelationship Name="ovs_ovs_cysafetyassessment_ovs_cyaction_safetyassessmentid">
    <EntityRelationshipType>OneToMany</EntityRelationshipType>
    <IsCustomizable>1</IsCustomizable>
    <IntroducedVersion>1.0.0.0</IntroducedVersion>
    <IsHierarchical>0</IsHierarchical>
    <ReferencingEntityName>ovs_CYAction</ReferencingEntityName>
    <ReferencedEntityName>ovs_CYSafetyAssessment</ReferencedEntityName>
    <CascadeAssign>NoCascade</CascadeAssign>
    <CascadeDelete>RemoveLink</CascadeDelete>
    <CascadeReparent>NoCascade</CascadeReparent>
    <CascadeShare>NoCascade</CascadeShare>
    <CascadeUnshare>NoCascade</CascadeUnshare>
    <CascadeRollupView>NoCascade</CascadeRollupView>
    <IsValidForAdvancedFind>1</IsValidForAdvancedFind>
    <ReferencingAttributeName>ovs_safetyassessmentid</ReferencingAttributeName>
    <RelationshipDescription>
      <Descriptions>
        <Description description="" languagecode="1033" />
      </Descriptions>
    </RelationshipDescription>
    <EntityRelationshipRoles>
      <EntityRelationshipRole>
        <NavPaneDisplayOption>UseCollectionName</NavPaneDisplayOption>
        <NavPaneArea>Details</NavPaneArea>
        <NavPaneOrder>10000</NavPaneOrder>
        <NavigationPropertyName>ovs_safetyassessmentid_ovs_CYAction</NavigationPropertyName>
        <RelationshipRoleType>1</RelationshipRoleType>
      </EntityRelationshipRole>
      <EntityRelationshipRole>
        <NavigationPropertyName>ovs_ovs_cysafetyassessment_ovs_cyaction_safetyassessmentid</NavigationPropertyName>
        <RelationshipRoleType>0</RelationshipRoleType>
      </EntityRelationshipRole>
    </EntityRelationshipRoles>
  </EntityRelationship>
  <EntityRelationship Name="qm_cysafetyassessment_syresult">
    <EntityRelationshipType>OneToMany</EntityRelationshipType>
    <IsCustomizable>1</IsCustomizable>
    <IntroducedVersion>1.0.0.1</IntroducedVersion>
    <IsHierarchical>0</IsHierarchical>
    <ReferencingEntityName>qm_syresult</ReferencingEntityName>
    <ReferencedEntityName>ovs_CYSafetyAssessment</ReferencedEntityName>
    <CascadeAssign>NoCascade</CascadeAssign>
    <CascadeDelete>RemoveLink</CascadeDelete>
    <CascadeReparent>NoCascade</CascadeReparent>
    <CascadeShare>NoCascade</CascadeShare>
    <CascadeUnshare>NoCascade</CascadeUnshare>
    <CascadeRollupView>NoCascade</CascadeRollupView>
    <IsValidForAdvancedFind>1</IsValidForAdvancedFind>
    <ReferencingAttributeName>qm_CYSafetyAssessmentId</ReferencingAttributeName>
    <RelationshipDescription>
      <Descriptions>
        <Description description="Unique identifier for Safety Assessment associated with Questionnaire Result." languagecode="1033" />
        <Description description="Identificateur unique pour l'évaluation de la sécurité associé au résultat du questionnaire." languagecode="1036" />
      </Descriptions>
    </RelationshipDescription>
    <EntityRelationshipRoles>
      <EntityRelationshipRole>
        <NavPaneDisplayOption>UseCollectionName</NavPaneDisplayOption>
        <NavPaneArea>Details</NavPaneArea>
        <NavPaneOrder>10000</NavPaneOrder>
        <NavigationPropertyName>qm_CYSafetyAssessmentId</NavigationPropertyName>
        <RelationshipRoleType>1</RelationshipRoleType>
      </EntityRelationshipRole>
      <EntityRelationshipRole>
        <NavigationPropertyName>qm_cysafetyassessment_syresult</NavigationPropertyName>
        <RelationshipRoleType>0</RelationshipRoleType>
      </EntityRelationshipRole>
    </EntityRelationshipRoles>
  </EntityRelationship>
</EntityRelationships>