<?xml version="1.0" encoding="utf-8"?>
<AppModule>
  <UniqueName>ts_ROMRailSafety</UniqueName>
  <IntroducedVersion>1.0.20251104.1</IntroducedVersion>
  <WebResourceId>953b9fac-1e5e-e611-80d6-00155ded156f</WebResourceId>
  <OptimizedFor></OptimizedFor>
  <statecode>0</statecode>
  <statuscode>1</statuscode>
  <FormFactor>1</FormFactor>
  <ClientType>4</ClientType>
  <NavigationType>0</NavigationType>
  <AppModuleComponents>
    <AppModuleComponent type="1" schemaName="ts_action" />
    <AppModuleComponent type="1" schemaName="qm_rclegislation" />
    <AppModuleComponent type="1" schemaName="msdyn_workorder" />
    <AppModuleComponent type="1" schemaName="ovs_finding" />
    <AppModuleComponent type="1" schemaName="account" />
    <AppModuleComponent type="1" schemaName="qm_tylegislationsource" />
    <AppModuleComponent type="1" schemaName="msdyn_functionallocation" />
    <AppModuleComponent type="1" schemaName="ovs_questionnaire" />
    <AppModuleComponent type="1" schemaName="incident" />
    <AppModuleComponent type="60" id="{45b022a4-928d-eb11-b1ac-000d3ae92dbf}" />
    <AppModuleComponent type="60" id="{f3f3935c-b7dd-4dd4-a86b-2b0735f57d13}" />
    <AppModuleComponent type="62" schemaName="ts_ROMRailSafety" />
  </AppModuleComponents>
  <AppModuleRoleMaps>
    <Role id="{5ccc89d2-67be-f011-bbd3-7c1e52549bb6}" />
    <Role id="{ef56a65a-65be-f011-bbd2-6045bd5d2567}" />
    <Role id="{627090ff-40a3-4053-8790-584edc5be201}" />
    <Role id="{119f245c-3cc8-4b62-b31c-d1a046ced15d}" />
  </AppModuleRoleMaps>
  <LocalizedNames>
    <LocalizedName description="ROM Rail Safety" languagecode="1033" />
  </LocalizedNames>
  <appsettings>
    <appsetting settingdefinitionid.uniquename="AppChannel">
      <iscustomizable>1</iscustomizable>
      <value>1</value>
    </appsetting>
    <appsetting settingdefinitionid.uniquename="AsyncOnSave">
      <iscustomizable>1</iscustomizable>
      <value>true</value>
    </appsetting>
    <appsetting settingdefinitionid.uniquename="msdyn_enablertecopilot">
      <iscustomizable>1</iscustomizable>
      <value>true</value>
    </appsetting>
    <appsetting settingdefinitionid.uniquename="msdyn_rtecopilotdefaultonruncompleted">
      <iscustomizable>1</iscustomizable>
      <value>true</value>
    </appsetting>
  </appsettings>
</AppModule>