<environmentvariabledefinition schemaname="ts_FindingsReportFlowURL">
  <defaultvalue>https://prod-26.canadacentral.logic.azure.com:443/workflows/93fd254f93b04c16998cd52dcbb22d44/triggers/manual/paths/invoke?api-version=2016-06-01&amp;sp=%2Ftriggers%2Fmanual%2Frun&amp;sv=1.0&amp;sig=7kcQ2SpCBVxRAYHLWagu7X0pvWEBpaXfXdi1IW6HGL8</defaultvalue>
  <description default="The URL to trigger the findings report Flow">
    <label description="The URL to trigger the findings report Flow" languagecode="1033" />
  </description>
  <displayname default="Findings Report Flow URL">
    <label description="Findings Report Flow URL" languagecode="1033" />
  </displayname>
  <introducedversion>1.0.20220506.1</introducedversion>
  <iscustomizable>1</iscustomizable>
  <isrequired>0</isrequired>
  <secretstore>0</secretstore>
  <type>100000000</type>
</environmentvariabledefinition>