<?xml version="1.0" encoding="utf-8"?>
<CanvasApp xmlns:xsi="http://www.w3.org/2001/XMLSchema-instance">
  <Name>ts_fileupload_2bf02</Name>
  <AppVersion>2023-06-27T15:11:07Z</AppVersion>
  <Status>Ready</Status>
  <CreatedByClientVersion>3.23063.14.0</CreatedByClientVersion>
  <MinClientVersion>3.23063.14.0</MinClientVersion>
  <Tags>{"primaryDeviceWidth":"450","primaryDeviceHeight":"500","supportsPortrait":"true","supportsLandscape":"true","primaryFormFactor":"Tablet","publisherVersion":"3.23063.14","minimumRequiredApiVersion":"2.2.0","hasComponent":"false","hasUnlockedComponent":"false","isUnifiedRootApp":"false","sienaVersion":"20230627T142030Z-3.23062.17.0"}</Tags>
  <IsCdsUpgraded>0</IsCdsUpgraded>
  <GalleryItemId xsi:nil="true"></GalleryItemId>
  <BackgroundColor>RGBA(0,176,240,1)</BackgroundColor>
  <DisplayName>File Upload</DisplayName>
  <Description xsi:nil="true"></Description>
  <CommitMessage xsi:nil="true"></CommitMessage>
  <Publisher xsi:nil="true"></Publisher>
  <AuthorizationReferences>[]</AuthorizationReferences>
  <ConnectionReferences>{"3258d0bf-7de6-41b9-996a-a2261e92dad1":{"id":"/providers/microsoft.powerapps/apis/shared_sharepointonline","displayName":"SharePoint","iconUri":"https://connectoricons-prod.azureedge.net/u/shgogna/globalperconnector-train1/1.0.1639.3310/sharepointonline/icon.png","dataSources":["General - Général"],"dependencies":[],"dependents":[],"parameterHints":{},"parameterHintsV2":{},"isOnPremiseConnection":false,"bypassConsent":false,"dataSets":{"https://034gc.sharepoint.com/sites/Dynamics365Development":{"dataSources":{"General - Général":{"tableName":"28e27f11-5081-4a6d-9725-17ad668b6ebd"}}}},"apiTier":"Standard","actions":["providers/PowerPlatform.Governance/Operations/Read"]},"91d15cb4-841b-42a4-90dd-e5f0ab77b863":{"id":"/providers/microsoft.powerapps/apis/shared_logicflows","displayName":"Logic flows","iconUri":"https://connectoricons-prod.azureedge.net/releases/v1.0.1636/1.0.1636.3297/logicflows/icon.png","dataSources":["UploadFileToDocumentLibrary"],"dependencies":["6529b72c-2ca2-43e0-9720-3c85d06a6599"],"dependents":[],"parameterHints":{"workflowName":{"value":"b292ebf5-8cba-4d5f-95a4-61b99ff320c9"},"workflowEntityId":{"value":"d06e63b9-eef3-ed11-8849-0022483c5061"},"6529b72c-2ca2-43e0-9720-3c85d06a6599":{"value":"shared_sharepointonline"}},"parameterHintsV2":{"workflowName":{"value":"b292ebf5-8cba-4d5f-95a4-61b99ff320c9"},"workflowEntityId":{"value":"d06e63b9-eef3-ed11-8849-0022483c5061"},"shared_sharepointonline":{"value":"6529b72c-2ca2-43e0-9720-3c85d06a6599"}},"isOnPremiseConnection":false,"bypassConsent":false,"dataSets":{},"apiTier":"Standard","actions":["Run"]},"6529b72c-2ca2-43e0-9720-3c85d06a6599":{"id":"/providers/microsoft.powerapps/apis/shared_sharepointonline","displayName":"SharePoint","iconUri":"https://connectoricons-prod.azureedge.net/u/shgogna/globalperconnector-train1/1.0.1639.3310/sharepointonline/icon.png","dataSources":[],"dependencies":[],"dependents":["91d15cb4-841b-42a4-90dd-e5f0ab77b863"],"parameterHints":{},"parameterHintsV2":{},"isOnPremiseConnection":false,"bypassConsent":false,"dataSets":{},"apiTier":"Standard","actions":["providers/PowerPlatform.Governance/Operations/Read"]}}</ConnectionReferences>
  <DatabaseReferences>{"default.cds":{"databaseDetails":{"referenceType":"Environmental","environmentName":"default.cds","overrideValues":{"status":"NotSpecified"}},"dataSources":{"Files":{"entitySetName":"ts_files","logicalName":"ts_file"},"File Categories":{"entitySetName":"ts_filecategories","logicalName":"ts_filecategory"},"File Sub-Categories":{"entitySetName":"ts_filesubcategories","logicalName":"ts_filesubcategory"}}}}</DatabaseReferences>
  <AppComponents>[]</AppComponents>
  <AppComponentDependencies>[]</AppComponentDependencies>
  <CanConsumeAppPass>1</CanConsumeAppPass>
  <CanvasAppType>2</CanvasAppType>
  <BypassConsent>0</BypassConsent>
  <AdminControlBypassConsent>0</AdminControlBypassConsent>
  <EmbeddedApp xsi:nil="true"></EmbeddedApp>
  <IntroducedVersion>1.0</IntroducedVersion>
  <CdsDependencies>{"cdsdependencies":[{"dependencyid":"d06e63b9-eef3-ed11-8849-0022483c5061","componenttype":29,"componenttypeplatformname":"Workflow"},{"logicalname":"ts_file","componenttype":1},{"logicalname":"ts_filecategory","componenttype":1},{"logicalname":"ts_filesubcategory","componenttype":1}]}</CdsDependencies>
  <IsCustomizable>1</IsCustomizable>
  <BackgroundImageUri>/CanvasApps/ts_fileupload_2bf02_BackgroundImageUri</BackgroundImageUri>
  <DocumentUri>/CanvasApps/ts_fileupload_2bf02_DocumentUri.msapp</DocumentUri>
</CanvasApp>